[
  {
    "title": "Data Analyst",
    "company": "Maxgen Technologies Private Limited",
    "location": "Pune",
    "link": "https://internshala.com/internship/detail/data-analyst-internship-in-pune-at-maxgen-technologies-private-limited1749142785",
    "stipend": "₹ 7,000 - 12,000 /month",
    "duration": "N/A",
    "work_model": "On Site",
    "date_posted": "Jun 22"
  },
  {
    "title": "Data Analyst (Marketing)",
    "company": "Astrotalk",
    "location": "Noida",
    "link": "https://internshala.com/internship/detail/data-analyst-marketing-internship-in-noida-at-astrotalk1748923511",
    "stipend": "₹ 20,000 - 25,000 /month",
    "duration": "N/A",
    "work_model": "On Site",
    "date_posted": "Jun 22"
  },
  {
    "title": "Financial Data Analyst",
    "company": "Indika AI Private Limited",
    "location": "Work from home",
    "link": "https://internshala.com/internship/detail/work-from-home-financial-data-analyst-internship-at-indika-ai-private-limited1748592697",
    "stipend": "₹ 3,000 - 5,000 lump sum",
    "duration": "N/A",
    "work_model": "On Site",
    "date_posted": "Jun 22"
  },
  {
    "title": "Medical Data Analyst",
    "company": "Indika AI Private Limited",
    "location": "Work from home",
    "link": "https://internshala.com/internship/detail/work-from-home-part-time-medical-data-analyst-internship-at-indika-ai-private-limited1748408351",
    "stipend": "₹ 2,000 - 4,000 /month",
    "duration": "N/A",
    "work_model": "On Site",
    "date_posted": "Jun 22"
  },
  {
    "title": "Data Analysis",
    "company": "Skillboat Technologies Private Limited",
    "location": "Ghaziabad",
    "link": "https://internshala.com/internship/detail/data-analytics-internship-in-ghaziabad-at-skillboat-technologies-private-limited1749460799",
    "stipend": "₹ 8,000 - 12,000 /month",
    "duration": "N/A",
    "work_model": "On Site",
    "date_posted": "Jun 22"
  },
  {
    "title": "Power Bi Data Analyst",
    "company": "Pianalytix Edutech Private Limted",
    "location": "Work from home",
    "link": "https://internshala.com/internship/detail/work-from-home-power-bi-data-analyst-internship-at-pianalytix-edutech-private-limted1750079007",
    "stipend": "₹ 15,000 - 20,000 /month",
    "duration": "N/A",
    "work_model": "On Site",
    "date_posted": "Jun 21"
  },
  {
    "title": "Artificial Intelligence (AI)",
    "company": "Ethical Den",
    "location": "Kolkata",
    "link": "https://internshala.com/internship/detail/artificial-intelligence-ai-internship-in-kolkata-at-ethical-den1750417335",
    "stipend": "₹ 6,000 - 10,000 /month",
    "duration": "N/A",
    "work_model": "On Site",
    "date_posted": "Jun 22"
  },
  {
    "title": "Data Science",
    "company": "Primetrade.ai",
    "location": "Work from home",
    "link": "https://internshala.com/internship/detail/work-from-home-data-science-internship-at-primetradeai1750411499",
    "stipend": "₹ 10,000 - 15,000 /month",
    "duration": "N/A",
    "work_model": "On Site",
    "date_posted": "Jun 21"
  },
  {
    "title": "Web Development",
    "company": "Addcomposites Oy",
    "location": "Work from home",
    "link": "https://internshala.com/internship/detail/work-from-home-web-development-internship-at-addcomposites-oy1750406342",
    "stipend": "₹ 10,000 - 15,000 /month",
    "duration": "N/A",
    "work_model": "On Site",
    "date_posted": "Jun 21"
  },
  {
    "title": "Data Analytics",
    "company": "Talent Corner HR Services",
    "location": "Mumbai",
    "link": "https://internshala.com/internship/detail/data-analytics-internship-in-mumbai-at-talent-corner-hr-services1750404689",
    "stipend": "₹ 15,000 lump sum",
    "duration": "N/A",
    "work_model": "On Site",
    "date_posted": "Jun 21"
  },
  {
    "title": "Angular Developer Trainee",
    "company": "Biwa",
    "location": "Remote",
    "link": "https://remoteok.com/remote-jobs/15478-remote-angular-developer-trainee-biwa",
    "stipend": "N/A",
    "duration": "N/A",
    "work_model": "Remote",
    "date_posted": "Jun 21"
  },
  {
    "title": "Customer Experience",
    "company": "Food Square",
    "location": "Mumbai",
    "link": "https://internshala.com/internship/detail/customer-experience-internship-in-mumbai-at-food-square1749283379",
    "stipend": "₹ 8,000 - 10,000 /month",
    "duration": "N/A",
    "work_model": "On Site",
    "date_posted": "Jun 21"
  },
  {
    "title": "Full Stack Development",
    "company": "Pixel AI Media",
    "location": "Work from home",
    "link": "https://internshala.com/internship/detail/work-from-home-part-time-full-stack-development-internship-at-pixel-ai-media1750417126",
    "stipend": "₹ 4,000 - 5,000 /month",
    "duration": "N/A",
    "work_model": "On Site",
    "date_posted": "Jun 21"
  },
  {
    "title": "Tech",
    "company": "UNIABROAD",
    "location": "Mysuru, Bangalore",
    "link": "https://internshala.com/internship/detail/tech-internship-in-multiple-locations-at-uniabroad1750415184",
    "stipend": "₹ 7,500 - 8,000 /month",
    "duration": "N/A",
    "work_model": "On Site",
    "date_posted": "Jun 21"
  },
  {
    "title": "Software Developer",
    "company": "Talent Corner HR Services",
    "location": "Mumbai",
    "link": "https://internshala.com/internship/detail/software-developer-internship-in-mumbai-at-talent-corner-hr-services1750411971",
    "stipend": "₹ 15,000 lump sum",
    "duration": "N/A",
    "work_model": "On Site",
    "date_posted": "Jun 21"
  },
  {
    "title": "Python Development",
    "company": "Primetrade.ai",
    "location": "Work from home",
    "link": "https://internshala.com/internship/detail/work-from-home-python-development-internship-at-primetradeai1750411388",
    "stipend": "₹ 10,000 - 15,000 /month",
    "duration": "N/A",
    "work_model": "On Site",
    "date_posted": "Jun 21"
  },
  {
    "title": "SQL Analyst",
    "company": "ClearTax",
    "location": "Bangalore",
    "link": "https://internshala.com/internship/detail/sql-analyst-internship-in-bangalore-at-cleartax1750406274",
    "stipend": "₹ 25,000 - 30,000 /month",
    "duration": "N/A",
    "work_model": "On Site",
    "date_posted": "Jun 21"
  },
  {
    "title": "Full Stack Developer",
    "company": "Talent Corner HR Services",
    "location": "Mumbai",
    "link": "https://internshala.com/internship/detail/full-stack-developer-internship-in-mumbai-at-talent-corner-hr-services1750405474",
    "stipend": "₹ 15,000 lump sum",
    "duration": "N/A",
    "work_model": "On Site",
    "date_posted": "Jun 21"
  },
  {
    "title": "Graphic Designer Intern",
    "company": "Orufy Technologies Private Limited",
    "location": "Jaipur",
    "link": "https://internshala.com/internship/detail/ui-ux-design-internship-in-jaipur-at-orufy-technologies-private-limited1749037663",
    "stipend": "₹ 5,000 - 10,000 /month",
    "duration": "N/A",
    "work_model": "On Site",
    "date_posted": "Jun 22"
  },
  {
    "title": "Shopify Developer",
    "company": "Fashionpur India",
    "location": "Ghaziabad",
    "link": "https://internshala.com/internship/detail/shopify-developer-internship-in-ghaziabad-at-fashionpur-india1748259920",
    "stipend": "₹ 12,000 - 15,000 /month",
    "duration": "N/A",
    "work_model": "On Site",
    "date_posted": "Jun 21"
  },
  {
    "title": "Business Development And Growth",
    "company": "Be Rolling Media",
    "location": "Delhi                                                                (Hybrid)",
    "link": "https://internshala.com/internship/detail/business-development-and-growth-internship-in-delhi-at-be-rolling-media1748938216",
    "stipend": "₹ 6,000 /month",
    "duration": "N/A",
    "work_model": "On Site",
    "date_posted": "Jun 21"
  },
  {
    "title": "Video Editor & Photographer (Female)",
    "company": "Astha Sharma",
    "location": "Delhi, Gurgaon                                                                (Hybrid)",
    "link": "https://internshala.com/internship/detail/part-time-video-editor-photographer-female-internship-in-multiple-locations-at-astha-sharma1748331987",
    "stipend": "₹ 5,000 /month",
    "duration": "N/A",
    "work_model": "On Site",
    "date_posted": "Jun 22"
  },
  {
    "title": "WordPress Development",
    "company": "Orufy Technologies Private Limited",
    "location": "Jaipur, Rajasthan",
    "link": "https://internshala.com/internship/detail/wordpress-development-internship-in-multiple-locations-at-orufy-technologies-private-limited1749626907",
    "stipend": "₹ 5,000 - 10,000 /month",
    "duration": "N/A",
    "work_model": "On Site",
    "date_posted": "Jun 22"
  },
  {
    "title": "Business Development (Sales)",
    "company": "Sidh Sidhi Gems",
    "location": "Jaipur",
    "link": "https://internshala.com/internship/detail/business-development-sales-internship-in-jaipur-at-sidh-sidhi-gems1748684401",
    "stipend": "₹ 5,000-10,000 /month",
    "duration": "N/A",
    "work_model": "On Site",
    "date_posted": "Jun 21"
  },
  {
    "title": "Architecture",
    "company": "HK Design",
    "location": "Gurgaon",
    "link": "https://internshala.com/internship/detail/architecture-internship-in-gurgaon-at-hk-design1748945552",
    "stipend": "₹ 10,000 - 15,000 /month",
    "duration": "N/A",
    "work_model": "On Site",
    "date_posted": "Jun 21"
  },
  {
    "title": "UI/UX Design",
    "company": "Beeyond Tech",
    "location": "Mumbai",
    "link": "https://internshala.com/internship/detail/ui-ux-design-internship-in-mumbai-at-beeyond-tech1749806739",
    "stipend": "₹ 8,000 - 12,000 /month",
    "duration": "N/A",
    "work_model": "On Site",
    "date_posted": "Jun 22"
  },
  {
    "title": "Content and Social Media Marketing",
    "company": "Vaatalya - Community & Nature Retreat",
    "location": "Solan, Shimla Division, Badi Dhar",
    "link": "https://internshala.com/internship/detail/retreat-life-digital-content-internship-in-multiple-locations-at-vaatalya-community-nature-retreat1750248663",
    "stipend": "₹ 3,500 - 6,000 /month",
    "duration": "N/A",
    "work_model": "On Site",
    "date_posted": "Jun 21"
  },
  {
    "title": "Telecalling",
    "company": "Basiya Group",
    "location": "Rajkot",
    "link": "https://internshala.com/internship/detail/telecalling-internship-in-rajkot-at-basiya-group1749126996",
    "stipend": "₹ 8,000 - 18,000 /month",
    "duration": "N/A",
    "work_model": "On Site",
    "date_posted": "Jun 22"
  },
  {
    "title": "Sales",
    "company": "UTM DELIGHT",
    "location": "Bhopal",
    "link": "https://internshala.com/internship/detail/sales-internship-in-bhopal-at-utm-delight1749037411",
    "stipend": "₹ 10,000 - 15,000 /month",
    "duration": "N/A",
    "work_model": "On Site",
    "date_posted": "Jun 22"
  },
  {
    "title": "Architecture",
    "company": "Parabola Architects",
    "location": "Pune, Mumbai, Maharashtra, Punjab                                                                (Hybrid)",
    "link": "https://internshala.com/internship/detail/architecture-internship-in-multiple-locations-at-parabola-architects1750328728",
    "stipend": "₹ 7,000 - 13,000 /month",
    "duration": "N/A",
    "work_model": "On Site",
    "date_posted": "Jun 22"
  },
  {
    "title": "Sales and Marketing",
    "company": "Anakin Management Consultants Pvt. Ltd.",
    "location": "Mumbai",
    "link": "https://internshala.com/internship/detail/sales-and-marketing-internship-in-mumbai-at-anakin-management-consultants-pvt-ltd1750159641",
    "stipend": "₹ 30,000 - 35,000 /month",
    "duration": "N/A",
    "work_model": "On Site",
    "date_posted": "Jun 21"
  },
  {
    "title": "Business Development (Sales)",
    "company": "SkyGrow Ecom Business Management Services",
    "location": "Mumbai, Goregaon Kh",
    "link": "https://internshala.com/internship/detail/business-development-sales-internship-in-mumbai-at-skygrow-ecom-business-management-services1749124790",
    "stipend": "₹ 10,000 /month",
    "duration": "N/A",
    "work_model": "On Site",
    "date_posted": "Jun 22"
  },
  {
    "title": "iOS App Development",
    "company": "199 Developments Private Limited",
    "location": "Ahmedabad",
    "link": "https://internshala.com/internship/detail/ios-app-development-internship-in-ahmedabad-at-199-developments-private-limited1748423384",
    "stipend": "₹ 5,000 - 12,000 /month",
    "duration": "N/A",
    "work_model": "On Site",
    "date_posted": "Jun 22"
  },
  {
    "title": "Architecture",
    "company": "Collabtec Design Build Private Limited",
    "location": "Thane, Mumbai",
    "link": "https://internshala.com/internship/detail/architecture-internship-in-thane-at-collabtec-design-build-private-limited1750314822",
    "stipend": "₹ 9,000 - 10,000 /month",
    "duration": "N/A",
    "work_model": "On Site",
    "date_posted": "Jun 21"
  },
  {
    "title": "Software Engineer Internship",
    "company": "HENNGE K.K",
    "location": "Remote",
    "link": "https://remoteok.com/remote-jobs/102971-remote-software-engineer-internship-hennge-k-k",
    "stipend": "N/A",
    "duration": "N/A",
    "work_model": "Remote",
    "date_posted": "Jun 22"
  },
  {
    "title": "IOS Developer Intern Sparrow",
    "company": "Sports AI Startup",
    "location": "Remote",
    "link": "https://remoteok.com/remote-jobs/100690-remote-ios-developer-intern-sparrow-sports-ai-startup",
    "stipend": "N/A",
    "duration": "N/A",
    "work_model": "Remote",
    "date_posted": "Jun 22"
  },
  {
    "title": "Summer Software Engineering Internship",
    "company": "Snowplow Analytics",
    "location": "Remote",
    "link": "https://remoteok.com/remote-jobs/66244-remote-summer-software-engineering-internship-snowplow-analytics",
    "stipend": "N/A",
    "duration": "N/A",
    "work_model": "Remote",
    "date_posted": "Jun 22"
  },
  {
    "title": "Junior Meteor Developer Intern",
    "company": "DreamLap",
    "location": "Remote",
    "link": "https://remoteok.com/remote-jobs/16863-remote-junior-meteor-developer-intern-dreamlap",
    "stipend": "N/A",
    "duration": "N/A",
    "work_model": "Remote",
    "date_posted": "Jun 22"
  },
  {
    "title": "PHP Developer Intern",
    "company": "BIWA",
    "location": "Remote",
    "link": "https://remoteok.com/remote-jobs/15480-remote-php-developer-intern-biwa",
    "stipend": "N/A",
    "duration": "N/A",
    "work_model": "Remote",
    "date_posted": "Jun 22"
  },
  {
    "title": "React Native Developer",
    "company": "Social Learning",
    "location": "Remote",
    "link": "https://remoteok.com/remote-jobs/15467-remote-react-native-developer-social-learning",
    "stipend": "N/A",
    "duration": "N/A",
    "work_model": "Remote",
    "date_posted": "Jun 21"
  },
  {
    "title": "Back End Developer",
    "company": "SMTP",
    "location": "Remote",
    "link": "https://remoteok.com/remote-jobs/12866-remote-back-end-developer-smtp",
    "stipend": "N/A",
    "duration": "N/A",
    "work_model": "Remote",
    "date_posted": "Jun 21"
  },
  {
    "title": "JQM PhoneGap Mobile app developer",
    "company": "Creatella",
    "location": "Remote",
    "link": "https://remoteok.com/remote-jobs/10539-remote-jqm-phonegap-mobile-app-developer-creatella",
    "stipend": "N/A",
    "duration": "N/A",
    "work_model": "Remote",
    "date_posted": "Jun 21"
  },
  {
    "title": "SOFTWARE ENGINEERING INTERNSHIP",
    "company": "Advanon",
    "location": "Remote",
    "link": "https://remoteok.com/remote-jobs/7763-remote-software-engineering-internship-advanon",
    "stipend": "N/A",
    "duration": "N/A",
    "work_model": "Remote",
    "date_posted": "Jun 22"
  },
  {
    "title": "Software Developer Internship",
    "company": "Phidato",
    "location": "Remote",
    "link": "https://remoteok.com/remote-jobs/6881-remote-software-developer-internship-phidato",
    "stipend": "N/A",
    "duration": "N/A",
    "work_model": "Remote",
    "date_posted": "Jun 22"
  },
  {
    "title": "Software Developer Internship",
    "company": "The Banyan Roots",
    "location": "Remote",
    "link": "https://remoteok.com/remote-jobs/6880-remote-software-developer-internship-the-banyan-roots",
    "stipend": "N/A",
    "duration": "N/A",
    "work_model": "Remote",
    "date_posted": "Jun 22"
  },
  {
    "title": "Data Analytics",
    "company": "Graps Marketing Pvt Ltd",
    "location": "Bhopal",
    "link": "https://internshala.com/internship/detail/data-analytics-internship-in-bhopal-at-graps-marketing-pvt-ltd1750491197",
    "stipend": "₹ 2,000 - 3,000 /month",
    "duration": "N/A",
    "work_model": "On Site",
    "date_posted": "Jun 22"
  },
  {
    "title": "Data Science Mentor",
    "company": "DevTown",
    "location": "Work from home",
    "link": "https://internshala.com/internship/detail/work-from-home-part-time-data-science-mentor-internship-at-devtown1750493846",
    "stipend": "₹ 10,000 /month",
    "duration": "N/A",
    "work_model": "On Site",
    "date_posted": "Jun 22"
  },
  {
    "title": "Machine Learning",
    "company": "Optimspace",
    "location": "Work from home",
    "link": "https://internshala.com/internship/detail/work-from-home-part-time-machine-learning-internship-at-optimspace1750564546",
    "stipend": "₹ 7,500 - 15,000 /month",
    "duration": "N/A",
    "work_model": "On Site",
    "date_posted": "Jun 22"
  },
  {
    "title": "Full Stack Development",
    "company": "DeepNexus.in",
    "location": "Work from home",
    "link": "https://internshala.com/internship/detail/work-from-home-full-stack-development-internship-at-deepnexusin1750489674",
    "stipend": "₹ 17,000 - 23,000 /month",
    "duration": "N/A",
    "work_model": "On Site",
    "date_posted": "Jun 22"
  },
  {
    "title": "AI/Prompt Engineer",
    "company": "DeepNexus.in",
    "location": "Work from home",
    "link": "https://internshala.com/internship/detail/work-from-home-ai-prompt-engineer-internship-at-deepnexusin1750488429",
    "stipend": "₹ 17,000 - 26,000 /month",
    "duration": "N/A",
    "work_model": "On Site",
    "date_posted": "Jun 22"
  },
  {
    "title": "Data Science",
    "company": "Emoolar Technology Private Limited",
    "location": "Work from home",
    "link": "https://internshala.com/internship/detail/work-from-home-part-time-data-science-internship-at-emoolar-technology-private-limited1750479140",
    "stipend": "₹ 5,000 - 7,000 /month",
    "duration": "N/A",
    "work_model": "On Site",
    "date_posted": "Jun 22"
  },
  {
    "title": "Digital Marketing",
    "company": "IBOg Enterprise",
    "location": "Vadodara",
    "link": "https://internshala.com/internship/detail/digital-marketing-internship-in-vadodara-at-ibog-enterprise1750220566",
    "stipend": "₹ 7,000 - 12,000 /month",
    "duration": "N/A",
    "work_model": "On Site",
    "date_posted": "Jun 21"
  },
  {
    "title": "Field Sales",
    "company": "Kaizen Infotech Solutions Private Limited",
    "location": "Thane, Navi Mumbai, Mumbai, Sion Koliwada                                                                (Hybrid)",
    "link": "https://internshala.com/internship/detail/field-sales-internship-in-multiple-locations-at-kaizen-infotech-solutions-private-limited1746101279",
    "stipend": "₹ 8,000 /month",
    "duration": "N/A",
    "work_model": "On Site",
    "date_posted": "Jun 21"
  },
  {
    "title": "Video Content Creator",
    "company": "Naiplus Solution Private Limited",
    "location": "Ahmedabad                                                                (Hybrid)",
    "link": "https://internshala.com/internship/detail/part-time-video-content-creator-internship-in-ahmedabad-at-naiplus-solution-private-limited1749629181",
    "stipend": "₹ 2,000 - 5,000 /month",
    "duration": "N/A",
    "work_model": "On Site",
    "date_posted": "Jun 22"
  },
  {
    "title": "Artificial Intelligence (AI)",
    "company": "Across The Globe (ATG)",
    "location": "Work from home",
    "link": "https://internshala.com/internship/detail/work-from-home-artificial-intelligence-ai-internship-at-across-the-globe-atg1750503551",
    "stipend": "₹ 2,500 - 10,000 /month",
    "duration": "N/A",
    "work_model": "On Site",
    "date_posted": "Jun 22"
  },
  {
    "title": "Swaraj Fellowship & Social Entrepreneurship",
    "company": "Hamari Pahchan NGO",
    "location": "Work from home",
    "link": "https://internshala.com/internship/detail/work-from-home-part-time-swaraj-fellowship-social-entrepreneurship-internship-at-hamari-pahchan-ngo1750154956",
    "stipend": "Unpaid",
    "duration": "N/A",
    "work_model": "On Site",
    "date_posted": "Jun 22"
  },
  {
    "title": "AI/ML",
    "company": "Trivy Technologies Private Limited",
    "location": "Work from home",
    "link": "https://internshala.com/internship/detail/work-from-home-ai-ml-internship-at-trivy-technologies-private-limited1749445925",
    "stipend": "₹ 2,000 - 3,000 /month",
    "duration": "N/A",
    "work_model": "On Site",
    "date_posted": "Jun 22"
  },
  {
    "title": "AI/ML Engineer",
    "company": "Bditto",
    "location": "Work from home",
    "link": "https://internshala.com/internship/detail/work-from-home-ai-ml-engineer-internship-at-bditto1748434102",
    "stipend": "₹ 10,000 /month",
    "duration": "N/A",
    "work_model": "On Site",
    "date_posted": "Jun 22"
  },
  {
    "title": "ML/AI Software Developer",
    "company": "Supervaisor.AI",
    "location": "Work from home",
    "link": "https://internshala.com/internship/detail/work-from-home-ml-ai-software-developer-internship-at-supervaisorai1750049531",
    "stipend": "₹ 16,000 - 50,000 /month",
    "duration": "N/A",
    "work_model": "On Site",
    "date_posted": "Jun 22"
  },
  {
    "title": "Academic Counselor",
    "company": "YES Germany",
    "location": "Coimbatore, Kerala Estate, Kochi                                                                (Hybrid)",
    "link": "https://internshala.com/internship/detail/academic-counselor-internship-in-multiple-locations-at-yes-germany1749633613",
    "stipend": "₹ 15,000 - 25,000 /month",
    "duration": "N/A",
    "work_model": "On Site",
    "date_posted": "Jun 22"
  },
  {
    "title": "Data Science",
    "company": "BlackHole Infiverse LLP",
    "location": "Mumbai",
    "link": "https://internshala.com/internship/detail/data-science-internship-in-mumbai-at-blackhole-infiverse-llp1750615173",
    "stipend": "₹ 5,000 - 8,000 /month",
    "duration": "N/A",
    "work_model": "On Site",
    "date_posted": "Jun 22"
  },
  {
    "title": "AIML Engineer",
    "company": "Subash Vijay Associates (SVA)",
    "location": "Mumbai",
    "link": "https://internshala.com/internship/detail/aiml-engineer-internship-in-mumbai-at-subash-vijay-associates-sva1750615078",
    "stipend": "₹ 5,000 - 8,000 /month",
    "duration": "N/A",
    "work_model": "On Site",
    "date_posted": "Jun 22"
  },
  {
    "title": "Software Development",
    "company": "Phurti - Instant Groceries",
    "location": "Work from home",
    "link": "https://internshala.com/internship/detail/work-from-home-software-development-internship-at-phurti-instant-groceries1750607368",
    "stipend": "₹ 10,000 - 15,000 /month",
    "duration": "N/A",
    "work_model": "On Site",
    "date_posted": "Jun 22"
  },
  {
    "title": "Python Development",
    "company": "Maxgen Technologies Private Limited",
    "location": "Ahmedabad",
    "link": "https://internshala.com/internship/detail/python-development-internship-in-ahmedabad-at-maxgen-technologies-private-limited1750574195",
    "stipend": "₹ 7,000 - 12,000 /month",
    "duration": "N/A",
    "work_model": "On Site",
    "date_posted": "Jun 22"
  },
  {
    "title": "AI/ML Project Coordination",
    "company": "Tellis Technologies Private Limited",
    "location": "Work from home",
    "link": "https://internshala.com/internship/detail/work-from-home-ai-ml-project-coordination-internship-at-tellis-technologies-private-limited1748954536",
    "stipend": "₹ 5,000 - 6,000 /month",
    "duration": "N/A",
    "work_model": "On Site",
    "date_posted": "Jun 22"
  },
  {
    "title": "Digital Marketing",
    "company": "Boss Naari",
    "location": "Pune                                                                (Hybrid)",
    "link": "https://internshala.com/internship/detail/digital-marketing-internship-in-pune-at-boss-naari1749719898",
    "stipend": "₹ 5,000 - 10,000 /month",
    "duration": "N/A",
    "work_model": "On Site",
    "date_posted": "Jun 22"
  },
  {
    "title": "Illustration/Graphic Design",
    "company": "Go Stops",
    "location": "Delhi",
    "link": "https://internshala.com/internship/detail/illustration-graphic-design-internship-in-delhi-at-go-stops1749558112",
    "stipend": "₹ 10,000 - 15,000 /month",
    "duration": "N/A",
    "work_model": "On Site",
    "date_posted": "Jun 22"
  }
]